maxent/__init__.py
maxent/core.py
maxent/hyper.py
maxent/version.py
maxent_infer-1.0.0.dist-info/LICENSE
maxent_infer-1.0.0.dist-info/METADATA
maxent_infer-1.0.0.dist-info/WHEEL
maxent_infer-1.0.0.dist-info/top_level.txt
maxent_infer-1.0.0.dist-info/RECORD
