Metadata-Version: 2.1
Name: maxent-infer
Version: 1.0.0
Summary: Maximum entropy inference Keras implementation
Home-page: https://github.com/ur-whitelab/maxent
Author: Mehrad Ansari <Mehrad.ansari@rochester.edu>, Rainier Barrett <rainier.barrett@gmail.com>, Andrew White <andrew.white@rochester.edu>
Author-email: andrew.white@rochester.edu
License: GPL v2
Platform: UNKNOWN
Classifier: Development Status :: 2 - Pre-Alpha
Classifier: License :: OSI Approved :: GNU General Public License v2 (GPLv2)
Classifier: Programming Language :: Python
Classifier: Programming Language :: Python :: 3
Classifier: Programming Language :: Python :: 3.8
Classifier: Programming Language :: Python :: 3.5
Classifier: Programming Language :: Python :: 3.6
Classifier: Programming Language :: Python :: 3.7
License-File: LICENSE
Requires-Dist: numpy
Requires-Dist: tensorflow
Requires-Dist: tensorflow-probability
